neurosis/__init__.py
neurosis/__main__.py
neurosis/_version.py
neurosis/constants.py
neurosis/data/__init__.py
neurosis/data/accessors.py
neurosis/data/files.py
neurosis/data/dinov2/LICENSE.dinov2.md
neurosis/data/dinov2/__init__.py
neurosis/data/dinov2/acquire.py
neurosis/data/fonts/NotoSansMono.ttf
neurosis/data/lpips/alex_lpips_v0.1.safetensors
neurosis/data/lpips/vgg_lpips_v0.1.safetensors
neurosis/dataset/__init__.py
neurosis/dataset/base.py
neurosis/dataset/loaders.py
neurosis/dataset/utils.py
neurosis/dataset/aspect/__init__.py
neurosis/dataset/aspect/base.py
neurosis/dataset/aspect/bucket.py
neurosis/dataset/aspect/lists.py
neurosis/dataset/aspect/sampler.py
neurosis/dataset/imagefolder/__init__.py
neurosis/dataset/imagefolder/aspect.py
neurosis/dataset/imagefolder/meme.py
neurosis/dataset/imagefolder/nobucket.py
neurosis/dataset/imagefolder/nocaption.py
neurosis/dataset/mongo/__init__.py
neurosis/dataset/mongo/aspect.py
neurosis/dataset/mongo/base.py
neurosis/dataset/mongo/nobucket.py
neurosis/dataset/mongo/nocaption.py
neurosis/dataset/mongo/settings.py
neurosis/dataset/processing/__init__.py
neurosis/dataset/processing/transform.py
neurosis/dataset/processing/caption/__init__.py
neurosis/dataset/processing/caption/clean.py
neurosis/dataset/processing/caption/meta.py
neurosis/dataset/processing/caption/rating.py
neurosis/fsdp/__init__.py
neurosis/fsdp/diffusionpolicy.py
neurosis/models/__init__.py
neurosis/models/autoencoder.py
neurosis/models/autoencoder_hf.py
neurosis/models/diffusion.py
neurosis/models/utils.py
neurosis/models/text_encoder/__init__.py
neurosis/models/text_encoder/clip.py
neurosis/models/text_encoder/clip_t5.py
neurosis/models/text_encoder/t5.py
neurosis/modules/__init__.py
neurosis/modules/attention.py
neurosis/modules/distributions.py
neurosis/modules/ema.py
neurosis/modules/guidance.py
neurosis/modules/layers.py
neurosis/modules/regularizers.py
neurosis/modules/autoencoding/__init__.py
neurosis/modules/autoencoding/losses/__init__.py
neurosis-0.1.3.dist-info/LICENSE.md
neurosis-0.1.3.dist-info/METADATA
neurosis-0.1.3.dist-info/WHEEL
neurosis-0.1.3.dist-info/entry_points.txt
neurosis-0.1.3.dist-info/top_level.txt
neurosis-0.1.3.dist-info/RECORD
