Metadata-Version: 2.1
Name: neurosis
Version: 0.1.3
Summary: A neural network trainer (for weebs)
Author-email: Andi Powers-Holmes <aholmes@omnom.net>
License: The extensive modifications made to the original code are released/relicensed under:
Keywords: deep-learning,diffusers,machine-learning,neural-networks,pytorch-lightning,pytorch,stable-diffusion,transformers
Classifier: Programming Language :: Python :: 3
Requires-Python: >=3.10
License-File: LICENSE.md
Requires-Dist: accelerate >=0.26.1
Requires-Dist: chardet ==5.1.0
Requires-Dist: colorama <0.5.0,>=0.4.3
Requires-Dist: colorcet <4.0.0,>=3.0.1
Requires-Dist: crc32c >=2.3
Requires-Dist: diffusers >=0.26.1
Requires-Dist: einops >=0.6.1
Requires-Dist: fsspec >=2024.4.0
Requires-Dist: jsonargparse[argcomplete,fsspec,omegaconf,signatures] <5.0.0,>=4.27.1
Requires-Dist: kornia >=0.7.0
Requires-Dist: lightning[extra] >=2.2.1
Requires-Dist: natsort >=8.4.0
Requires-Dist: ninja >=1.11.0
Requires-Dist: numpy >=1.24.3
Requires-Dist: open-clip-torch >=2.2.0
Requires-Dist: opencv-contrib-python-headless <4.7.0,>=4.6.0.66
Requires-Dist: pandas >=2.0.0
Requires-Dist: pillow <11.0.0,>=10.0.0
Requires-Dist: pudb >=2022.1.3
Requires-Dist: pydantic <2.6.0,>=2.5.0
Requires-Dist: pydantic-settings <2.2.0,>=2.0.0
Requires-Dist: pytorch-optimizer >=2.12.0
Requires-Dist: rich <14.0.0,>=13.0.0
Requires-Dist: safetensors >=0.4.2
Requires-Dist: scipy <1.12.0,>=1.11.1
Requires-Dist: sentencepiece >=0.1.99
Requires-Dist: shellingham <2.0.0,>=1.5.0
Requires-Dist: tokenizers >=0.13.3
Requires-Dist: torch >=2.1.0
Requires-Dist: torchmetrics >=1.3.0
Requires-Dist: torchvision
Requires-Dist: tqdm >=4.65.0
Requires-Dist: transformers >=4.36.0
Requires-Dist: typer <1.0.0,>=0.9.0
Requires-Dist: wandb <0.18.0,>=0.17.0
Provides-Extra: all
Requires-Dist: neurosis[dev] ; extra == 'all'
Requires-Dist: neurosis[extra] ; extra == 'all'
Requires-Dist: neurosis[mongo] ; extra == 'all'
Requires-Dist: neurosis[multinode] ; extra == 'all'
Requires-Dist: neurosis[vae] ; extra == 'all'
Provides-Extra: dev
Requires-Dist: ruff >=0.0.289 ; extra == 'dev'
Requires-Dist: setuptools-scm >=8.0.0 ; extra == 'dev'
Requires-Dist: pre-commit >=3.0.0 ; extra == 'dev'
Requires-Dist: tabulate >=0.8.9 ; extra == 'dev'
Provides-Extra: extra
Requires-Dist: bitsandbytes >=0.41.0 ; extra == 'extra'
Requires-Dist: datasets >=2.13.0 ; extra == 'extra'
Requires-Dist: hf-transfer <1.0.0,>=0.1.4 ; extra == 'extra'
Requires-Dist: nvidia-ml-py <13.0.0,>=12.0.0 ; extra == 'extra'
Requires-Dist: adlfs >=2024.4.0 ; extra == 'extra'
Requires-Dist: s3fs >=2024.4.0 ; extra == 'extra'
Provides-Extra: mongo
Requires-Dist: pyarrow <17.0.0,>=13.0.0 ; extra == 'mongo'
Requires-Dist: pymongoarrow <1.6.0,>=1.4.0 ; extra == 'mongo'
Requires-Dist: zstandard >=0.22.0 ; extra == 'mongo'
Provides-Extra: multinode
Requires-Dist: torchelastic <0.3.0,>=0.2.2 ; extra == 'multinode'
Provides-Extra: novae
Requires-Dist: neurosis[dev] ; extra == 'novae'
Requires-Dist: neurosis[extra] ; extra == 'novae'
Requires-Dist: neurosis[mongo] ; extra == 'novae'
Requires-Dist: neurosis[multinode] ; extra == 'novae'
